zxing_tkinter_utils/__init__.py
zxing_tkinter_utils/core.py
zxing_tkinter_utils/example.py
zxing_tkinter_utils-1.0.2.dist-info/METADATA
zxing_tkinter_utils-1.0.2.dist-info/WHEEL
zxing_tkinter_utils-1.0.2.dist-info/top_level.txt
zxing_tkinter_utils-1.0.2.dist-info/RECORD
