Metadata-Version: 2.1
Name: zxing-tkinter-utils
Version: 1.0.2
Summary: tkinter实用工具
License: MIT
